nninit.py
nninit-0.1.dev2.dist-info/DESCRIPTION.rst
nninit-0.1.dev2.dist-info/METADATA
nninit-0.1.dev2.dist-info/RECORD
nninit-0.1.dev2.dist-info/WHEEL
nninit-0.1.dev2.dist-info/metadata.json
nninit-0.1.dev2.dist-info/top_level.txt
