Metadata-Version: 2.0
Name: nninit
Version: 0.1.dev2
Summary: initialization schemes for the PyTorch nn package
Home-page: https://github.com/alykhantejani/nninit
Author: Alykhan Tejani
Author-email: alykhan.tejani@gmail.com
License: UNKNOWN
Platform: UNKNOWN
Requires-Dist: numpy
Requires-Dist: scipy
Requires-Dist: torch
